cellbender/VERSION.txt
cellbender/__init__.py
cellbender/base_cli.py
cellbender/monitor.py
cellbender/remove_background/__init__.py
cellbender/remove_background/argparser.py
cellbender/remove_background/checkpoint.py
cellbender/remove_background/cli.py
cellbender/remove_background/consts.py
cellbender/remove_background/downstream.py
cellbender/remove_background/estimation.py
cellbender/remove_background/exceptions.py
cellbender/remove_background/model.py
cellbender/remove_background/posterior.py
cellbender/remove_background/report.ipynb
cellbender/remove_background/report.py
cellbender/remove_background/run.py
cellbender/remove_background/sparse_utils.py
cellbender/remove_background/train.py
cellbender/remove_background/data/__init__.py
cellbender/remove_background/data/dataprep.py
cellbender/remove_background/data/dataset.py
cellbender/remove_background/data/io.py
cellbender/remove_background/data/priors.py
cellbender/remove_background/data/extras/__init__.py
cellbender/remove_background/data/extras/simulate.py
cellbender/remove_background/distributions/NegativeBinomialPoissonConv.py
cellbender/remove_background/distributions/NegativeBinomialPoissonConvApprox.py
cellbender/remove_background/distributions/NullDist.py
cellbender/remove_background/distributions/__init__.py
cellbender/remove_background/tests/__init__.py
cellbender/remove_background/tests/conftest.py
cellbender/remove_background/tests/mckp_memory_profiling.py
cellbender/remove_background/tests/test_checkpoint.py
cellbender/remove_background/tests/test_dataprep.py
cellbender/remove_background/tests/test_dataset.py
cellbender/remove_background/tests/test_downstream.py
cellbender/remove_background/tests/test_estimation.py
cellbender/remove_background/tests/test_infer.py
cellbender/remove_background/tests/test_integration.py
cellbender/remove_background/tests/test_io.py
cellbender/remove_background/tests/test_monitor.py
cellbender/remove_background/tests/test_posterior.py
cellbender-0.3.0.dist-info/LICENSE
cellbender-0.3.0.dist-info/METADATA
cellbender-0.3.0.dist-info/WHEEL
cellbender-0.3.0.dist-info/entry_points.txt
cellbender-0.3.0.dist-info/top_level.txt
cellbender-0.3.0.dist-info/RECORD
