Metadata-Version: 2.1
Name: cellbender
Version: 0.3.0
Summary: A software package for eliminating technical artifacts from high-throughput single-cell RNA sequencing (scRNA-seq) data
Author: Stephen Fleming, Mehrtash Babadi
License: BSD (3-Clause)
Project-URL: Homepage, http://github.com/broadinstitute/CellBender
Project-URL: Documentation, http://cellbender.readthedocs.io
Keywords: scRNA-seq,bioinformatics
Classifier: Development Status :: 4 - Beta
Classifier: Intended Audience :: Science/Research
Classifier: License :: OSI Approved :: BSD License
Classifier: Programming Language :: Python :: 3.7
Classifier: Topic :: Scientific/Engineering :: Bio-Informatics
License-File: LICENSE
Requires-Dist: numpy
Requires-Dist: scipy
Requires-Dist: tables
Requires-Dist: pandas
Requires-Dist: pyro-ppl >=1.8.4
Requires-Dist: torch
Requires-Dist: matplotlib
Requires-Dist: anndata >=0.7
Requires-Dist: loompy
Requires-Dist: ipython
Requires-Dist: jupyter
Requires-Dist: jupyter-contrib-nbextensions
Requires-Dist: notebook <7.0.0
Requires-Dist: nbconvert <7.0.0
Requires-Dist: psutil
Provides-Extra: dev
Requires-Dist: pytest ; extra == 'dev'
Requires-Dist: scikit-learn ; extra == 'dev'
Provides-Extra: docs
Requires-Dist: sphinx >=2.1 ; extra == 'docs'
Requires-Dist: sphinx-rtd-theme ; extra == 'docs'
Requires-Dist: sphinx-autodoc-typehints ; extra == 'docs'
Requires-Dist: sphinxcontrib-programoutput ; extra == 'docs'
Requires-Dist: sphinx-argparse ; extra == 'docs'
